{
  "h1": "AIを使ってわずか数分で素晴らしいBluesミュージックビデオを作成",
  "direct_answer": "AIブルースミュージックビデオジェネレーターは、オーディオまたはテキストプロンプトから自動的にプロフェッショナルなブルース風ミュージックビデオを作成するツールです。Tuneeのプラットフォームは高度な機械学習を使用して、ミシシッピデルタと使い古されたギター弦を特徴とする、あなたのトラックのエネルギーとスタイルに合わせたAIシーン生成による憂鬱なビジュアルを制作します。Tuneeを使えば、ビデオ編集の経験がなくても、アイデアから完成したブルースミュージックビデオまで数分で完成させることができます。",
  "meta_description": "Tuneeの AIブルースミュージックビデオジェネレーターでプロフェッショナルなブルースミュージックビデオを作成。憂鬱なビジュアル、高速エクスポート、経験不要。",
  "prompts": [
    "ミシシッピデルタと掃くようなカメラムーブメントを持つ憂鬱なシーン。ビートに合わせて脈動するドラマチックなライティングに包まれている",
    "使い古されたギター弦に没入したアーティスト、ビデオの全フレームとカットを通じて魂のあるエネルギーが放射されている",
    "薄暗いバーが抽象的に変形・流動し、スローモーションで音楽の憂鬱な本質を完璧にキャプチャしている",
    "ミシシッピデルタのクローズアップショットがソウルパフォーマーに溶け込み、曲のリズムに従う魂のあるビジュアルジャーニーを作成している",
    "手前に使い古されたギター弦を持つ荒れた環境の広いエスタブリッシングショット、深い感情的な共鳴を喚起している",
    "薄暗いバーと古い褪色したトーン間のダイナミックなカット、憂鬱なカラーグレーディングとシャープなモーショングラフィックスでテンションを構築している",
    "ソウルパフォーマーとミシシッピデルタのソウルフルなモンタージュ、スムーズなトランジションとドロップに合わせたビジュアルビートが重ねられている",
    "古い褪色したトーンと使い古されたギター弦が光、色、動きの憂鬱な爆発で収束する最終シーケンス"
  ],
  "personas": {
    "musicians": "ブルースギタリストは、ブルースミュージックビデオを使用してアーティスティックアイデンティティを視覚的に定義し、ファンベースを増やし、ストリーミングプラットフォームで目立つ必要があります。",
    "creators": "デルタブルースアーティストは、ブルースミュージックビデオの美学を使用して、エンゲージメントを促進し、コラボレーションの機会を引き付ける独特なビジュアルブランドを構築しています。",
    "labels": "レコードレーベルは、新しいリリースを宣伝するための高速でプロフェッショナルなブルースミュージックビデオ制作に依存し、すべてのデジタルチャネルにわたってコスト効率的に行っています。",
    "brands": "ブランドと広告主は、ブルースミュージックビデオの美学を使用して、ターゲットオーディエンスと感情的に共鳴する憂鬱なキャンペーンコンテンツを作成しています。"
  },
  "faqs": [
    {
      "q": "ビデオ編集経験なしでブルースミュージックビデオを作成できますか？",
      "a": "はい。Tuneeの AIがすべてのビデオ制作を自動的に処理します。オーディオをアップロードするか、テキストプロンプトを入力して、ブルーススタイルを選択するだけで、AIが数分でビデオを生成します。"
    },
    {
      "q": "ブルースミュージックビデオを4K解像度でエクスポートできますか？",
      "a": "もちろんです。Tuneeはブルースミュージックビデオを最大4K解像度でエクスポートでき、YouTube、ストリーミングプラットフォーム、大画面ディスプレイに対応しています。"
    },
    {
      "q": "ブルースミュージックビデオのビジュアルスタイルをカスタマイズするにはどうすればよいですか？",
      "a": "シーン、気分、設定を説明するテキストプロンプトを使用してビジュアルをガイドできます。Tuneeの AIがあなたの入力を解釈して、ブルースの美学に合ったミシシッピデルタにインスパイアされたビジュアルを生成します。"
    },
    {
      "q": "Tuneeのブルースミュージックビデオジェネレーターを商用プロジェクトに使用できますか？",
      "a": "はい。Tuneeで作成されたビデオは、ストリーミングリリース、ブランドキャンペーン、ソーシャルメディアコンテンツを含む商用目的で使用できます。"
    },
    {
      "q": "ブルースだけに機能しますか、他のジャンルにも対応していますか？",
      "a": "Tuneeはブルース以外の幅広いジャンルとビジュアルスタイルをサポートしています。同じプラットフォームを使用してポップ、ヒップホップ、クラシック、その他数十のスタイルのミュージックビデオを生成できます。"
    }
  ]
}