{
  "h1": "AI로 3D 뮤직 비디오를 만드는 가장 빠른 방법",
  "direct_answer": "AI 3D 뮤직 비디오 생성기는 오디오 또는 텍스트 프롬프트로부터 자동으로 전문적인 3D 스타일의 뮤직 비디오를 만드는 도구입니다. Tunee의 플랫폼은 고급 머신러닝을 사용하여 실시간 CGI 렌더링과 원클릭 내보내기를 특징으로 하는 미래지향적인 비주얼을 생성하며, 당신의 트랙의 에너지와 스타일에 맞게 조정됩니다. Tunee를 사용하면 아이디어에서 완성된 3D 뮤직 비디오까지 단 몇 분 만에 만들 수 있으며, 비디오 편집 경험이 전혀 필요하지 않습니다.",
  "meta_description": "Tunee의 AI 3D 뮤직 비디오 생성기로 미래지향적인 3D 비주얼을 즉시 만들어보세요. 편집 기술이 필요 없습니다 — YouTube, TikTok 등을 위해 4K로 내보내세요.",
  "prompts": [
    "드라마틱한 조명이 가득한 미래지향적인 장면, CGI 렌더링과 광활한 카메라 움직임이 비트에 맞춰 맥박을 이룹니다",
    "추상적인 3D 도형에 몰입한 아티스트, 비디오의 모든 프레임과 컷을 통해 광나는 에너지가 방출됩니다",
    "미래지향적인 음악의 본질을 완벽하게 포착하면서 슬로우 모션으로 변형되고 흐르는 추상적인 유리 반사",
    "CGI 렌더링이 체적 조명으로 녹아드는 클로즈업 샷, 노래의 리듬을 따르는 광나는 시각적 여정을 만듭니다",
    "전경의 추상적인 3D 도형이 있는 기술 환경의 광활한 앞놀이 샷, 깊은 정서적 공명을 불러일으킵니다",
    "유리 반사와 모션 그래픽 사이의 역동적인 컷, 미래지향적인 색감 보정과 날카로운 모션 그래픽으로 긴장을 만듭니다",
    "체적 조명과 CGI 렌더링의 광나는 몽타주, 부드러운 트랜지션과 드롭과 일치하는 시각적 비트가 겹겹이 쌓입니다",
    "최종 시퀀스는 모션 그래픽과 추상적인 3D 도형이 빛, 색상, 움직임의 미래지향적인 폭발로 수렴합니다"
  ],
  "personas": {
    "musicians": "일렉트로닉 뮤직 아티스트는 자신의 예술적 정체성을 시각적으로 정의하고, 팬베이스를 확대하며, 스트리밍 플랫폼에서 돋보이기 위해 3D 뮤직 비디오가 필요합니다.",
    "creators": "모션 그래픽 크리에이터는 3D 뮤직 비디오 미학을 사용하여 독특한 시각적 브랜드를 구축하고 참여도를 높이며 협업 기회를 유치합니다.",
    "labels": "레코드 레이블은 새로운 릴리스를 모든 디지털 채널에서 비용 효율적으로 홍보하기 위해 빠르고 전문적인 3D 뮤직 비디오 제작을 의존합니다.",
    "brands": "브랜드와 광고주는 3D 뮤직 비디오 미학을 사용하여 대상 고객과 정서적으로 공명하는 미래지향적인 캠페인 콘텐츠를 만듭니다."
  },
  "faqs": [
    {
      "q": "비디오 편집 경험이 없어도 3D 뮤직 비디오를 만들 수 있나요?",
      "a": "네 — Tunee의 AI가 모든 비디오 제작을 자동으로 처리합니다. 오디오를 업로드하거나 텍스트 프롬프트를 입력하고, 3D 스타일을 선택하면 AI가 몇 분 안에 비디오를 생성합니다."
    },
    {
      "q": "3D 뮤직 비디오를 4K 해상도로 내보낼 수 있나요?",
      "a": "물론입니다. Tunee는 3D 뮤직 비디오를 최대 4K 해상도로 내보내므로 YouTube, 스트리밍 플랫폼, 대형 디스플레이에 사용할 수 있습니다."
    },
    {
      "q": "3D 뮤직 비디오의 시각적 스타일을 어떻게 커스터마이즈하나요?",
      "a": "장면, 분위기, 설정을 설명하는 텍스트 프롬프트를 사용하여 비주얼을 안내할 수 있습니다. Tunee의 AI가 입력을 해석하고 3D 미학과 일치하는 CGI 렌더링 영감의 비주얼을 생성합니다."
    },
    {
      "q": "3D 뮤직 비디오에 가사나 자막을 추가하려면 어떻게 하나요?",
      "a": "Tunee는 내장 가사 및 자막 오버레이 옵션을 제공합니다. 가사를 입력하고 텍스트 스타일을 선택하면 AI가 자동으로 3D 뮤직 비디오에 동기화합니다."
    },
    {
      "q": "3D 뮤직 비디오의 여러 버전을 생성하여 비교할 수 있나요?",
      "a": "네. 다양한 프롬프트나 스타일 설정을 사용하여 3D 뮤직 비디오의 여러 변형을 생성한 다음 당신의 비전에 가장 잘 맞는 버전을 선택할 수 있습니다."
    }
  ]
}