{
  "h1": "AI로 Spotify Canvas 음악 뮤직비디오를 만드는 가장 빠른 방법",
  "direct_answer": "Spotify Canvas용 AI 음악 뮤직비디오는 오디오나 텍스트 프롬프트에서 자동으로 전문가 수준의 Spotify Canvas 스타일 뮤직비디오를 만드는 도구입니다. Tunee의 플랫폼은 고급 머신러닝을 사용하여 3-8초 루프 렌더링 자동화와 다중 스타일 내보내기 기능이 있는 분위기 있는 비주얼을 제작하며, 당신의 트랙의 에너지와 스타일에 맞춰집니다. Tunee를 사용하면 아이디어에서 완성된 Spotify Canvas 음악 뮤직비디오까지 몇 분 안에 만들 수 있으며, 비디오 편집 경험이 전혀 필요하지 않습니다.",
  "meta_description": "Tunee의 AI 음악 뮤직비디오로 Spotify Canvas 비주얼을 즉시 만들어보세요. 편집 스킬이 필요 없으며 — 4K로 내보내기 가능합니다...",
  "prompts": [
    "3-8초 루프와 넓은 카메라 움직임이 있는 분위기 있는 장면, 극적인 조명으로 가득 차 있고 비트에 맞춰 펄스됨",
    "9:16 세로 방향에 몰입된 세로 클로즈업 샷, 비디오의 모든 프레임과 컷을 통해 흘러나오는 에너지",
    "느린 모션으로 형태를 바꾸고 흐르는 추상적 움직임, 음악의 분위기 있는 본질을 완벽하게 포착함",
    "3-8초 루프로 녹아드는 분위기 있는 무드의 클로즈업 샷, 곡의 리듬을 따라가는 루핑 비주얼 여정을 만듦",
    "세로 9:16을 전경에 둔 주변 환경의 넓은 이스테블리싱 샷, 깊은 감정적 울림을 불러일으킴",
    "추상적 움직임과 텍스트 오버레이 없음 사이의 동적 컷, 분위기 있는 색 보정과 날카로운 모션 그래픽으로 긴장감을 높임",
    "분위기 있는 무드와 3-8초 루프의 루핑 몽타주, 부드러운 트랜지션과 드롭과 일치하는 비주얼 비트로 레이어됨",
    "텍스트 오버레이 없음과 세로 9:16이 분위기 있는 빛, 색상, 움직임의 폭발로 수렴하는 최종 시퀀스"
  ],
  "personas": {
    "musicians": "독립 뮤지션들은 플랫폼에서의 도달 범위를 최대화하기 위해 Spotify Canvas를 사용하며, 포맷 요구사항을 충족하고 즉시 주의를 끕니다.",
    "creators": "Spotify 아티스트들은 알고리즘 가시성을 높이고 매 업로드마다 팔로워를 늘리기 위해 완벽하게 포맷된 Spotify Canvas 콘텐츠에 의존합니다.",
    "labels": "레코드 레이블들은 전체 로스터에 대해 플랫폼에 최적화된 Spotify Canvas 비디오를 일괄 제작하며, 처리 시간을 주 단위에서 시간 단위로 단축합니다.",
    "brands": "이 플랫폼에서 유료 및 오가닉 캠페인을 진행하는 브랜드들은 Tunee를 사용하여 규모에 맞게 스크롤을 멈추게 하는 Spotify Canvas 비디오 광고를 제작합니다."
  },
  "faqs": [
    {
      "q": "비디오 편집 경험 없이도 Spotify Canvas 음악 뮤직비디오를 만들 수 있나요?",
      "a": "네 — Tunee의 AI가 모든 비디오 제작을 자동으로 처리합니다. 오디오를 업로드하거나 텍스트 프롬프트를 입력하고, Spotify Canvas 스타일을 선택하면, AI가 몇 분 안에 비디오를 생성합니다."
    },
    {
      "q": "Spotify Canvas 음악 뮤직비디오를 4K 해상도로 내보낼 수 있나요?",
      "a": "물론입니다. Tunee는 Spotify Canvas 음악 뮤직비디오를 최대 4K 해상도로 내보내며, YouTube, 스트리밍 플랫폼, 대형 디스플레이에 바로 사용할 수 있습니다."
    },
    {
      "q": "Spotify Canvas 음악 뮤직비디오의 비주얼 스타일을 어떻게 커스터마이즈하나요?",
      "a": "장면, 무드, 설정을 설명하는 텍스트 프롬프트를 사용하여 비주얼을 안내할 수 있습니다. Tunee의 AI가 당신의 입력을 해석하고 Spotify Canvas 미학과 일치하는 3-8초 루프 영감의 비주얼을 생성합니다."
    },
    {
      "q": "Spotify Canvas 음악 뮤직비디오의 여러 버전을 생성하여 비교할 수 있나요?",
      "a": "네. 다양한 프롬프트나 스타일 설정을 사용하여 Spotify Canvas 음악 뮤직비디오의 여러 변형을 생성한 후, 당신의 비전에 가장 잘 맞는 버전을 선택할 수 있습니다."
    },
    {
      "q": "Tunee의 Spotify Canvas 음악 뮤직비디오 생성기가 모바일 기기에서 작동하나요?",
      "a": "Tunee는 데스크톱과 모바일 모두에서 웹 브라우저를 통해 완전히 접근 가능하므로, 소프트웨어를 설치하지 않고도 어디서나 Spotify Canvas 음악 뮤직비디오를 만들 수 있습니다."
    }
  ]
}