{
  "h1": "使用AI将您的音乐转化为电影级音乐人视频",
  "direct_answer": "音乐人AI音乐视频是一种工具，可以从您的音频或文本提示自动创建专业的音乐人风格音乐视频。Tunee的平台使用先进的机器学习来生成专业视觉效果，具有自动化艺术家表演渲染和多风格导出功能，完全契合您音乐的能量和风格。使用Tunee，您可以在几分钟内从创意到完成的音乐人音乐视频，无需任何视频编辑经验。",
  "meta_description": "使用Tunee的AI音乐人音乐视频工具即时创建专业视觉效果。无需编辑技能——导出4K视频用于YouTube、TikTok等平台...",
  "prompts": [
    "专业场景展现艺术家表演和流畅的摄像机运动，沐浴在随节拍脉动的戏剧性灯光中",
    "竖屏特写镜头沉浸在工作室设置中，品牌能量通过视频的每一帧和每一个切镜散发出来",
    "抽象音乐宣传在慢动作中变形流动，完美捕捉音乐的专业本质",
    "艺术家表演特写镜头溶解为品牌形象，创造随歌曲节奏流动的品牌视觉之旅",
    "真实环境的宽幅建立镜头，前景中的工作室设置，唤起深深的情感共鸣",
    "音乐宣传和专业品质之间的动态切镜，通过专业色彩分级和锐利的动态图形营造紧张感",
    "艺术家品牌和艺术家表演的品牌蒙太奇，叠加流畅的过渡和与节拍下降匹配的视觉节奏",
    "最终序列展现专业品质和工作室设置汇聚成专业的光、色彩和运动爆发"
  ],
  "personas": {
    "musicians": "独立音乐人使用音乐人工具最大化平台覆盖率，确保他们的内容符合格式要求并立即吸引注意力。",
    "creators": "独奏音乐人依靠完美格式化的音乐人内容来提升算法可见性，通过每次上传增加粉丝。",
    "labels": "唱片公司为其全部艺人批量生产平台优化的音乐人视频，将周转时间从数周缩短到数小时。",
    "brands": "在此平台上运营付费和有机营销活动的品牌使用Tunee大规模制作引人瞩目的音乐人视频广告。"
  },
  "faqs": [
    {
      "q": "没有视频编辑经验也能创建音乐人音乐视频吗？",
      "a": "可以——Tunee的AI自动处理所有视频制作。只需上传您的音频或输入文本提示，选择音乐人风格，AI会在几分钟内生成您的视频。"
    },
    {
      "q": "支持以4K分辨率导出音乐人音乐视频吗？",
      "a": "绝对支持。Tunee可以导出最高4K分辨率的音乐人音乐视频，使其适合YouTube、流媒体平台和大屏幕显示。"
    },
    {
      "q": "如何自定义音乐人音乐视频的视觉风格？",
      "a": "您可以使用文本提示来引导视觉效果，描述场景、情绪和设置。Tunee的AI会解释您的输入并生成与您的音乐人美学相匹配的艺术家表演启发的视觉效果。"
    },
    {
      "q": "能用Tunee的音乐人音乐视频生成器进行商业项目吗？",
      "a": "可以。使用Tunee创建的视频可用于商业目的，包括流媒体发行、品牌营销活动和社交媒体内容。"
    },
    {
      "q": "如何向音乐人音乐视频添加歌词或字幕？",
      "a": "Tunee提供内置的歌词和字幕叠加选项。只需输入您的歌词并选择文本风格，AI会自动将其与您的音乐人音乐视频同步。"
    }
  ]
}